Metadata-Version: 2.1
Name: synapse-room-access-rules
Version: 1.0.0
Summary: Custom room access rules for Tchap
Home-page: https://github.com/matrix-org/synapse-room-access-rules
License: UNKNOWN
Platform: UNKNOWN
Classifier: Development Status :: 4 - Beta
Classifier: License :: OSI Approved :: Apache Software License
Classifier: Programming Language :: Python :: 3
Requires-Python: >=3.6
